odoo9_addon_l10n_es_aeat_mod115-9.0.1.0.0-py2.7-nspkg.pth
odoo9_addon_l10n_es_aeat_mod115-9.0.1.0.0.dist-info/DESCRIPTION.rst
odoo9_addon_l10n_es_aeat_mod115-9.0.1.0.0.dist-info/METADATA
odoo9_addon_l10n_es_aeat_mod115-9.0.1.0.0.dist-info/RECORD
odoo9_addon_l10n_es_aeat_mod115-9.0.1.0.0.dist-info/WHEEL
odoo9_addon_l10n_es_aeat_mod115-9.0.1.0.0.dist-info/metadata.json
odoo9_addon_l10n_es_aeat_mod115-9.0.1.0.0.dist-info/namespace_packages.txt
odoo9_addon_l10n_es_aeat_mod115-9.0.1.0.0.dist-info/top_level.txt
odoo_addons/l10n_es_aeat_mod115/README.rst
odoo_addons/l10n_es_aeat_mod115/__init__.py
odoo_addons/l10n_es_aeat_mod115/__openerp__.py
odoo_addons/l10n_es_aeat_mod115/data/aeat_export_mod115_data.xml
odoo_addons/l10n_es_aeat_mod115/data/tax_code_map_mod115_data.xml
odoo_addons/l10n_es_aeat_mod115/docs/DR115e15v11.xls
odoo_addons/l10n_es_aeat_mod115/i18n/bg.po
odoo_addons/l10n_es_aeat_mod115/i18n/cs.po
odoo_addons/l10n_es_aeat_mod115/i18n/es.po
odoo_addons/l10n_es_aeat_mod115/i18n/es_CO.po
odoo_addons/l10n_es_aeat_mod115/i18n/es_CR.po
odoo_addons/l10n_es_aeat_mod115/i18n/eu.po
odoo_addons/l10n_es_aeat_mod115/i18n/fr.po
odoo_addons/l10n_es_aeat_mod115/i18n/gl.po
odoo_addons/l10n_es_aeat_mod115/i18n/hr.po
odoo_addons/l10n_es_aeat_mod115/i18n/nl.po
odoo_addons/l10n_es_aeat_mod115/i18n/pl.po
odoo_addons/l10n_es_aeat_mod115/i18n/pt.po
odoo_addons/l10n_es_aeat_mod115/i18n/pt_BR.po
odoo_addons/l10n_es_aeat_mod115/i18n/ru.po
odoo_addons/l10n_es_aeat_mod115/i18n/sl.po
odoo_addons/l10n_es_aeat_mod115/i18n/sv.po
odoo_addons/l10n_es_aeat_mod115/i18n/tr.po
odoo_addons/l10n_es_aeat_mod115/i18n/vi.po
odoo_addons/l10n_es_aeat_mod115/models/__init__.py
odoo_addons/l10n_es_aeat_mod115/models/mod115.py
odoo_addons/l10n_es_aeat_mod115/security/ir.model.access.csv
odoo_addons/l10n_es_aeat_mod115/static/description/icon.png
odoo_addons/l10n_es_aeat_mod115/static/description/icon_source.svg
odoo_addons/l10n_es_aeat_mod115/tests/__init__.py
odoo_addons/l10n_es_aeat_mod115/tests/test_l10n_es_aeat_mod115.py
odoo_addons/l10n_es_aeat_mod115/views/mod115_view.xml
